gokite/__init__.py
gokite/exceptions.py
gokite/kite_client.py
gokite/langchain_tools.py
gokite/main.py
gokite/util.py
gokite/cli/__init__.py
gokite/cli/entry_point.py
gokite-0.0.14.dist-info/METADATA
gokite-0.0.14.dist-info/WHEEL
gokite-0.0.14.dist-info/entry_points.txt
gokite-0.0.14.dist-info/top_level.txt
gokite-0.0.14.dist-info/RECORD
