Metadata-Version: 2.1
Name: gokite
Version: 0.0.14
Summary: Python SDK for GoKite AI
Author: GoKite Labs
Author-email: support@gokite.ai
Project-URL: Homepage, https://gokite.ai
Project-URL: Source, https://github.com/gokite-ai/gokite-sdk-python
Keywords: gokite,client,cloud,AI,blockchain,infrastructure
Classifier: Topic :: System :: Distributed Computing
Classifier: Operating System :: OS Independent
Classifier: License :: OSI Approved :: Apache Software License
Classifier: Programming Language :: Python :: 3
Requires-Python: >=3.9
Requires-Dist: requests
Requires-Dist: typer
